{"series": [{"date": "2026-03-26", "close": 1905.0, "open": 1930.0, "high": 2045.0, "low": 1905.0, "volume": 1822331, "ma5": 1902.0, "ma20": 1805.75, "ma60": 1577.25, "macd_hist": 0.6481, "vol_ratio": 1.07}, {"date": "2026-03-27", "close": 1905.0, "open": 1865.0, "high": 1930.0, "low": 1850.0, "volume": 950287, "ma5": 1883.0, "ma20": 1815.5, "ma60": 1583.25, "macd_hist": -1.2576, "vol_ratio": 0.63}, {"date": "2026-03-30", "close": 1830.0, "open": 1850.0, "high": 1855.0, "low": 1785.0, "volume": 1030728, "ma5": 1876.0, "ma20": 1819.75, "ma60": 1588.0, "macd_hist": -7.9882, "vol_ratio": 0.73}, {"date": "2026-03-31", "close": 1750.0, "open": 1780.0, "high": 1820.0, "low": 1735.0, "volume": 1204454, "ma5": 1859.0, "ma20": 1819.25, "ma60": 1590.5, "macd_hist": -17.6912, "vol_ratio": 0.87}, {"date": "2026-04-01", "close": 1925.0, "open": 1855.0, "high": 1925.0, "low": 1855.0, "volume": 951877, "ma5": 1863.0, "ma20": 1833.25, "ma60": 1596.17, "macd_hist": -12.4346, "vol_ratio": 0.66}, {"date": "2026-04-02", "close": 1885.0, "open": 1940.0, "high": 2005.0, "low": 1880.0, "volume": 1659528, "ma5": 1859.0, "ma20": 1841.75, "ma60": 1600.83, "macd_hist": -11.7697, "vol_ratio": 1.39}, {"date": "2026-04-07", "close": 1850.0, "open": 1935.0, "high": 1945.0, "low": 1835.0, "volume": 1050433, "ma5": 1848.0, "ma20": 1842.0, "ma60": 1604.75, "macd_hist": -13.6718, "vol_ratio": 0.91}, {"date": "2026-04-08", "close": 1890.0, "open": 1900.0, "high": 1970.0, "low": 1870.0, "volume": 2693761, "ma5": 1860.0, "ma20": 1853.25, "ma60": 1609.17, "macd_hist": -12.2655, "vol_ratio": 2.28}, {"date": "2026-04-09", "close": 1840.0, "open": 1930.0, "high": 1945.0, "low": 1830.0, "volume": 1799758, "ma5": 1878.0, "ma20": 1857.75, "ma60": 1612.75, "macd_hist": -14.575, "vol_ratio": 1.19}, {"date": "2026-04-10", "close": 1865.0, "open": 1870.0, "high": 1890.0, "low": 1800.0, "volume": 1619609, "ma5": 1866.0, "ma20": 1857.75, "ma60": 1618.25, "macd_hist": -14.2729, "vol_ratio": 0.99}, {"date": "2026-04-13", "close": 1765.0, "open": 1855.0, "high": 1855.0, "low": 1685.0, "volume": 3075223, "ma5": 1842.0, "ma20": 1854.0, "ma60": 1622.83, "macd_hist": -20.2944, "vol_ratio": 1.74}, {"date": "2026-04-14", "close": 1730.0, "open": 1785.0, "high": 1795.0, "low": 1725.0, "volume": 2115377, "ma5": 1818.0, "ma20": 1852.75, "ma60": 1627.17, "macd_hist": -25.7693, "vol_ratio": 1.03}, {"date": "2026-04-15", "close": 1825.0, "open": 1760.0, "high": 1850.0, "low": 1750.0, "volume": 2061509, "ma5": 1805.0, "ma20": 1856.5, "ma60": 1634.17, "macd_hist": -22.2596, "vol_ratio": 0.91}, {"date": "2026-04-16", "close": 1900.0, "open": 1860.0, "high": 1960.0, "low": 1845.0, "volume": 2627654, "ma5": 1817.0, "ma20": 1864.25, "ma60": 1643.08, "macd_hist": -14.5282, "vol_ratio": 1.23}, {"date": "2026-04-17", "close": 1870.0, "open": 1875.0, "high": 1930.0, "low": 1840.0, "volume": 1609329, "ma5": 1818.0, "ma20": 1865.75, "ma60": 1651.5, "macd_hist": -11.2236, "vol_ratio": 0.7}, {"date": "2026-04-20", "close": 1895.0, "open": 1880.0, "high": 1930.0, "low": 1845.0, "volume": 1534913, "ma5": 1844.0, "ma20": 1861.75, "ma60": 1660.92, "macd_hist": -7.3315, "vol_ratio": 0.67}, {"date": "2026-04-21", "close": 1915.0, "open": 1915.0, "high": 1965.0, "low": 1855.0, "volume": 2014764, "ma5": 1881.0, "ma20": 1857.5, "ma60": 1671.25, "macd_hist": -3.5774, "vol_ratio": 1.01}, {"date": "2026-04-22", "close": 1985.0, "open": 1945.0, "high": 2015.0, "low": 1930.0, "volume": 2266952, "ma5": 1913.0, "ma20": 1863.5, "ma60": 1682.67, "macd_hist": 3.0923, "vol_ratio": 1.15}, {"date": "2026-04-23", "close": 1910.0, "open": 2055.0, "high": 2100.0, "low": 1850.0, "volume": 2865063, "ma5": 1915.0, "ma20": 1867.25, "ma60": 1693.17, "macd_hist": 1.9793, "vol_ratio": 1.42}, {"date": "2026-04-24", "close": 1915.0, "open": 1950.0, "high": 2045.0, "low": 1875.0, "volume": 3358988, "ma5": 1924.0, "ma20": 1867.75, "ma60": 1703.08, "macd_hist": 1.1475, "vol_ratio": 1.63}, {"date": "2026-04-27", "close": 2070.0, "open": 1930.0, "high": 2105.0, "low": 1880.0, "volume": 3728078, "ma5": 1959.0, "ma20": 1876.0, "ma60": 1716.25, "macd_hist": 10.1055, "vol_ratio": 1.55}, {"date": "2026-04-28", "close": 2085.0, "open": 2095.0, "high": 2180.0, "low": 2005.0, "volume": 2011241, "ma5": 1993.0, "ma20": 1885.0, "ma60": 1729.58, "macd_hist": 15.7725, "vol_ratio": 0.71}, {"date": "2026-04-29", "close": 2070.0, "open": 2065.0, "high": 2160.0, "low": 2045.0, "volume": 1477926, "ma5": 2010.0, "ma20": 1897.0, "ma60": 1742.67, "macd_hist": 17.1293, "vol_ratio": 0.52}, {"date": "2026-04-30", "close": 2070.0, "open": 2080.0, "high": 2115.0, "low": 1995.0, "volume": 1699332, "ma5": 2042.0, "ma20": 1913.0, "ma60": 1753.67, "macd_hist": 16.6315, "vol_ratio": 0.63}, {"date": "2026-05-04", "close": 2215.0, "open": 2180.0, "high": 2275.0, "low": 2110.0, "volume": 2481202, "ma5": 2102.0, "ma20": 1927.5, "ma60": 1767.58, "macd_hist": 24.2131, "vol_ratio": 1.01}, {"date": "2026-05-05", "close": 1995.0, "open": 2160.0, "high": 2165.0, "low": 1995.0, "volume": 3044220, "ma5": 2087.0, "ma20": 1933.0, "ma60": 1777.33, "macd_hist": 13.1127, "vol_ratio": 1.34}, {"date": "2026-05-06", "close": 1880.0, "open": 2015.0, "high": 2015.0, "low": 1805.0, "volume": 4817011, "ma5": 2046.0, "ma20": 1934.5, "ma60": 1785.0, "macd_hist": -2.4445, "vol_ratio": 2.25}, {"date": "2026-05-07", "close": 1920.0, "open": 1925.0, "high": 1950.0, "low": 1875.0, "volume": 1652661, "ma5": 2016.0, "ma20": 1936.0, "ma60": 1792.17, "macd_hist": -10.0821, "vol_ratio": 0.61}, {"date": "2026-05-08", "close": 1980.0, "open": 1925.0, "high": 2035.0, "low": 1900.0, "volume": 2672931, "ma5": 1998.0, "ma20": 1943.0, "ma60": 1800.42, "macd_hist": -11.0563, "vol_ratio": 0.98}, {"date": "2026-05-11", "close": 1995.0, "open": 2020.0, "high": 2055.0, "low": 1965.0, "volume": 1862387, "ma5": 1954.0, "ma20": 1949.5, "ma60": 1809.92, "macd_hist": -10.6495, "vol_ratio": 0.63}, {"date": "2026-05-12", "close": 1850.0, "open": 2020.0, "high": 2035.0, "low": 1845.0, "volume": 2567911, "ma5": 1925.0, "ma20": 1953.75, "ma60": 1817.33, "macd_hist": -19.585, "vol_ratio": 0.91}, {"date": "2026-05-13", "close": 1830.0, "open": 1835.0, "high": 1890.0, "low": 1805.0, "volume": 2026051, "ma5": 1915.0, "ma20": 1958.75, "ma60": 1822.25, "macd_hist": -25.8857, "vol_ratio": 0.75}, {"date": "2026-05-14", "close": 1780.0, "open": 1875.0, "high": 1885.0, "low": 1780.0, "volume": 2039927, "ma5": 1887.0, "ma20": 1956.5, "ma60": 1826.5, "macd_hist": -32.0603, "vol_ratio": 0.95}, {"date": "2026-05-15", "close": 1735.0, "open": 1820.0, "high": 1840.0, "low": 1725.0, "volume": 1581970, "ma5": 1838.0, "ma20": 1948.25, "ma60": 1829.58, "macd_hist": -37.4401, "vol_ratio": 0.71}, {"date": "2026-05-18", "close": 1735.0, "open": 1700.0, "high": 1745.0, "low": 1645.0, "volume": 914583, "ma5": 1786.0, "ma20": 1941.5, "ma60": 1832.75, "macd_hist": -39.0824, "vol_ratio": 0.45}, {"date": "2026-05-19", "close": 1770.0, "open": 1735.0, "high": 1815.0, "low": 1695.0, "volume": 1086415, "ma5": 1770.0, "ma20": 1935.25, "ma60": 1836.42, "macd_hist": -35.9734, "vol_ratio": 0.59}, {"date": "2026-05-20", "close": 1720.0, "open": 1770.0, "high": 1810.0, "low": 1710.0, "volume": 1035483, "ma5": 1748.0, "ma20": 1925.5, "ma60": 1838.75, "macd_hist": -35.392, "vol_ratio": 0.68}, {"date": "2026-05-21", "close": 1810.0, "open": 1770.0, "high": 1810.0, "low": 1755.0, "volume": 720876, "ma5": 1754.0, "ma20": 1916.75, "ma60": 1843.17, "macd_hist": -27.41, "vol_ratio": 0.54}, {"date": "2026-05-22", "close": 1795.0, "open": 1830.0, "high": 1845.0, "low": 1785.0, "volume": 926662, "ma5": 1766.0, "ma20": 1911.0, "ma60": 1848.42, "macd_hist": -21.8463, "vol_ratio": 0.87}, {"date": "2026-05-25", "close": 1745.0, "open": 1825.0, "high": 1825.0, "low": 1740.0, "volume": 1650500, "ma5": 1768.0, "ma20": 1902.5, "ma60": 1852.83, "macd_hist": -20.2739, "vol_ratio": 1.76}, {"date": "2026-05-26", "close": 1785.0, "open": 1750.0, "high": 1820.0, "low": 1705.0, "volume": 2312490, "ma5": 1771.0, "ma20": 1888.25, "ma60": 1856.67, "macd_hist": -15.4957, "vol_ratio": 2.13}, {"date": "2026-05-27", "close": 1740.0, "open": 1805.0, "high": 1840.0, "low": 1720.0, "volume": 1477013, "ma5": 1775.0, "ma20": 1871.0, "ma60": 1857.17, "macd_hist": -14.3479, "vol_ratio": 1.11}, {"date": "2026-05-28", "close": 1765.0, "open": 1765.0, "high": 1865.0, "low": 1730.0, "volume": 2987056, "ma5": 1766.0, "ma20": 1855.75, "ma60": 1857.5, "macd_hist": -11.0358, "vol_ratio": 2.11}, {"date": "2026-05-29", "close": 1930.0, "open": 1835.0, "high": 1940.0, "low": 1800.0, "volume": 3761596, "ma5": 1793.0, "ma20": 1848.75, "ma60": 1860.33, "macd_hist": 2.4188, "vol_ratio": 2.01}, {"date": "2026-06-01", "close": 2120.0, "open": 2040.0, "high": 2120.0, "low": 2040.0, "volume": 2680905, "ma5": 1868.0, "ma20": 1844.0, "ma60": 1868.25, "macd_hist": 23.1153, "vol_ratio": 1.1}, {"date": "2026-06-02", "close": 2190.0, "open": 2150.0, "high": 2245.0, "low": 2100.0, "volume": 4289581, "ma5": 1949.0, "ma20": 1853.75, "ma60": 1876.17, "macd_hist": 39.555, "vol_ratio": 1.62}, {"date": "2026-06-03", "close": 2085.0, "open": 2240.0, "high": 2260.0, "low": 2020.0, "volume": 3206397, "ma5": 2018.0, "ma20": 1864.0, "ma60": 1880.17, "macd_hist": 41.2066, "vol_ratio": 1.06}, {"date": "2026-06-04", "close": 1985.0, "open": 2020.0, "high": 2055.0, "low": 1955.0, "volume": 1101952, "ma5": 2062.0, "ma20": 1867.25, "ma60": 1885.5, "macd_hist": 33.7279, "vol_ratio": 0.33}, {"date": "2026-06-05", "close": 1950.0, "open": 1925.0, "high": 2065.0, "low": 1890.0, "volume": 1366732, "ma5": 2066.0, "ma20": 1865.75, "ma60": 1888.83, "macd_hist": 24.9898, "vol_ratio": 0.45}, {"date": "2026-06-08", "close": 1895.0, "open": 1760.0, "high": 1935.0, "low": 1760.0, "volume": 1231620, "ma5": 2021.0, "ma20": 1860.75, "ma60": 1889.33, "macd_hist": 14.5872, "vol_ratio": 0.49}, {"date": "2026-06-09", "close": 1950.0, "open": 1900.0, "high": 1950.0, "low": 1850.0, "volume": 1672167, "ma5": 1973.0, "ma20": 1865.75, "ma60": 1891.17, "macd_hist": 10.6732, "vol_ratio": 0.75}, {"date": "2026-06-10", "close": 1755.0, "open": 1890.0, "high": 1900.0, "low": 1755.0, "volume": 2328139, "ma5": 1907.0, "ma20": 1862.0, "ma60": 1891.17, "macd_hist": -4.9474, "vol_ratio": 1.36}, {"date": "2026-06-11", "close": 1750.0, "open": 1700.0, "high": 1790.0, "low": 1690.0, "volume": 939592, "ma5": 1860.0, "ma20": 1860.5, "ma60": 1891.17, "macd_hist": -14.9499, "vol_ratio": 0.61}, {"date": "2026-06-12", "close": 1825.0, "open": 1805.0, "high": 1855.0, "low": 1745.0, "volume": 1708257, "ma5": 1835.0, "ma20": 1865.0, "ma60": 1892.5, "macd_hist": -15.7673, "vol_ratio": 1.13}, {"date": "2026-06-15", "close": 1735.0, "open": 1880.0, "high": 1880.0, "low": 1735.0, "volume": 2039794, "ma5": 1803.0, "ma20": 1865.0, "ma60": 1890.75, "macd_hist": -21.2788, "vol_ratio": 1.29}, {"date": "2026-06-16", "close": 1725.0, "open": 1740.0, "high": 1765.0, "low": 1720.0, "volume": 969263, "ma5": 1758.0, "ma20": 1862.75, "ma60": 1886.58, "macd_hist": -24.2897, "vol_ratio": 0.56}, {"date": "2026-06-17", "close": 1715.0, "open": 1710.0, "high": 1760.0, "low": 1690.0, "volume": 958345, "ma5": 1750.0, "ma20": 1862.5, "ma60": 1881.83, "macd_hist": -25.5199, "vol_ratio": 0.6}, {"date": "2026-06-18", "close": 1755.0, "open": 1745.0, "high": 1765.0, "low": 1720.0, "volume": 814870, "ma5": 1751.0, "ma20": 1859.75, "ma60": 1880.0, "macd_hist": -22.3206, "vol_ratio": 0.62}, {"date": "2026-06-22", "close": 1820.0, "open": 1775.0, "high": 1830.0, "low": 1750.0, "volume": 1044735, "ma5": 1750.0, "ma20": 1861.0, "ma60": 1879.75, "macd_hist": -14.8663, "vol_ratio": 0.8}, {"date": "2026-06-23", "close": 1790.0, "open": 1820.0, "high": 1840.0, "low": 1760.0, "volume": 531437, "ma5": 1761.0, "ma20": 1863.25, "ma60": 1877.83, "macd_hist": -11.1647, "vol_ratio": 0.46}], "signals": [{"date": "2026-05-26", "type": "volume_surge", "label": "爆量2.1×"}, {"date": "2026-05-28", "type": "volume_surge", "label": "爆量2.1×"}, {"date": "2026-05-29", "type": "macd_positive", "label": "MACD轉正"}, {"date": "2026-05-29", "type": "volume_surge", "label": "爆量2.0×"}, {"date": "2026-06-01", "type": "golden_cross", "label": "黃金交叉"}], "selection_reasons": ["投信初登場", "外資初登場"]}